Workbook

Sheet Indicadores Adicionales
A2: Participación (%) del valor de la cuota de administración de su club respecto al valor total de los mantenimientos
A3: Participación (%) del valor de la cuota de administración de su club respecto al valor total de los servicios públicos
A4: Participación (%) del valor de la cuota de administración de su club respecto al valor total de la planta de personal
A5: Participación (%) del valor de la cuota de administración de su club respecto al valor total del impuesto predial
A6: Porcentaje de participación de los ingresos que genera su club por los eventos y torneos respecto a los ingresos totales. %.
A7: Porcentaje de participación de los ingresos de los restaurantes, torneos y eventos en los ingresos totales año
A8: Porcentaje de participación de los ingresos de las actividades deportivas en los ingresos totales año
A9: Porcentaje de participación de la cuota de sostenimiento en los ingresos totales año
A10: Porcentaje de participación de los gastos de personal en los ingresos totales año
A11: Porcentaje de participación de los gastos por servicios públicos en los ingresos totales año
A12: Porcentaje de participación de los gastos por impuestos en los ingresos totales
A13: Porcentaje de participación del valor de los inventarios en relación con los ingresos totales año.
... A20: Tiene una persona especial para la venta de las acciones? Le paga salario?

Sheet Dashboard_KPIs
A1: DASHBOARD DE KPIs - ANÁLISIS INTEGRAL DEL CLUB
A3: 📊 IDENTIDAD Y DIMENSIÓN DEL CLUB
A4: Indicador | B4: Valor | C4: Unidad | D4: Fuente
A5: Tipo de Club | B5: =CAP0_Identidad_Censo!E5 -> 0 | D5: CAP0
A6: Área Total Terreno | B6: =CAP0_Identidad_Censo!E8 -> 0 | C6: m² | D6: CAP0
A7: Socios Titulares | B7: =CAP0_Identidad_Censo!E11 -> 0 | C7: Cant. | D7: CAP0
A8: Comunidad Total | B8: =CAP0_Identidad_Censo!E12 -> 0 | C8: Vidas | D8: CAP0
A10: 💰 INDICADORES FINANCIEROS
A11: KPI Financiero | B11: Valor Calculado | C11: Unidad | D11: Fórmula
A12: Ingreso por Socio/Mes | B12: =IFERROR(CAP1_Financiero_CAPEX!E5/12/CAP0_Identidad_Censo!E11,0) -> 0 | C12: $/Socio | D12: F-01÷12÷C-01
A13: EBITDA por Socio/Año | B13: =IFERROR(CAP1_Financiero_CAPEX!E11/CAP0_Identidad_Censo!E11,0) -> 0 | C13: $/Socio | D13: F-04÷C-01
A14: Margen EBITDA | B14: =IFERROR(CAP1_Financiero_CAPEX!E11/CAP1_Financiero_CAPEX!E5,0) -> 0 | C14: % | D14: F-04÷F-01
A15: Gasto Servicios/m² | B15: =IFERROR(CAP1_Financiero_CAPEX!E12/CAP0_Identidad_Censo!E8,0) -> 0 | C15: $/m² | D15: G-01÷D-02
A16: Cuota vs Ingreso Total | B16: =IFERROR(CAP1_Financiero_CAPEX!E6/CAP1_Financiero_CAPEX!E5,0) -> 0 | C16: % | D16: F-02÷F-01
A17: A&B vs Ingreso Total | B17: =IFERROR(CAP1_Financiero_CAPEX!E7/CAP1_Financiero_CAPEX!E5,0) -> 0 | C17: % | D17: F-03÷F-01
A19: 👥 PRODUCTIVIDAD DE NÓMINA
A20: KPI Nómina | B20: Valor Calculado | C20: Unidad | D20: Fórmula
A21: Nómina Total Mensual | B21: =SUM(CAP2_Nomina!E5:E8) -> 0 | C21: $ Miles | D21: Suma N-01:N-04
A22: Nómina por Socio/Mes | B22: =IFERROR(SUM(CAP2_Nomina!E5:E8)/CAP0_Identidad_Censo!E11,0) -> 0 | C22: $/Socio | D22: Total÷C-01
A23: Ingreso por $ Nómina | B23: =IFERROR(CAP1_Financiero_CAPEX!E5/SUM(CAP2_Nomina!E5:E8)/12,0) -> 0 | C23: Ratio | D23: F-01÷Nómina÷12
A24: % Nómina Operativa A&B | B24: =IFERROR(CAP2_Nomina!E6/SUM(CAP2_Nomina!E5:E8),0) -> 0 | C24: % | D24: N-02÷Total
A25: % Nómina Deportiva | B25: =IFERROR(CAP2_Nomina!E7/SUM(CAP2_Nomina!E5:E8),0) -> 0 | C25: % | D25: N-03÷Total
A27: ⛳ EFICIENCIA DE INFRAESTRUCTURA
A28: KPI Infraestructura | B28: Valor Calculado | C28: Unidad | D28: Fórmula
A29: Socios por Cancha | B29: =IFERROR(CAP0_Identidad_Censo!E11/CAP3_Infraestructura_Uso!E8,0) -> 0 | C29: Socios/Cancha | D29: C-01÷S-03
A30: Rounds Mensuales Golf | B30: =CAP3_Infraestructura_Uso!E6 -> 0 | C30: Rounds | D30: S-02
A31: Ingresos Gym/Mes | B31: =CAP3_Infraestructura_Uso!E12 -> 0 | C31: Ingresos | D31: S-05
A32: Venta por Silla A&B/Mes | B32: =IFERROR(CAP1_Financiero_CAPEX!E7/12/CAP3_Infraestructura_Uso!E13,0) -> 0 | C32: $/Silla | D32: F-03÷12÷S-06
A34: 💳 TARIFAS Y GESTIÓN DE CARTERA
A35: Indicador Comercial | B35: Valor | C35: Unidad | D35: Fuente
A36: Cuota Sostenimiento | B36: =CAP4_Tarifas_Cartera!E5 -> 0 | C36: $ Pesos | D36: T-01
A37: Valor Acción/Título | B37: =CAP4_Tarifas_Cartera!E6 -> 0 | C37: $ Miles | D37: T-02
A38: Días de Cartera (DSO) | B38: =CAP4_Tarifas_Cartera!E17 -> 0 | C38: Días | D38: K-01
A40: ⚠️ INSTRUCCIONES: Completar las hojas CAP0 a CAP4 para ver los KPIs calculados automáticamente.

Sheet CAP0_Identidad_Censo
A1: CAPÍTULO 0: IDENTIDAD, CENSO Y DIMENSIÓN
A2: (Los Denominadores - Variables de Normalización)
A4: Código | B4: Categoría | C4: Variable | D4: Unidad | E4: Valor a Capturar
A5: P-01 | B5: Perfil | C5: Tipo de Club | D5: Código
C6: (1=Ciudad, 2=Campestre, 3=Mixto)
A7: D-01 | C7: Casa club/sedes | D7: Cant.
A8: D-02 | B8: Dimensión | C8: Área Total del Terreno | D8: m²
A9: D-03 | B9: Dimensión | C9: Área Total Construida | D9: m²
A10: D-04 | B10: Dimensión | C10: Cantidad de Sedes / Casas Club | D10: Cant.
A11: C-01 | B11: Censo | C11: Socios Titulares (Activos) | D11: Cant.
A12: C-02 | B12: Censo | C12: Comunidad Total (Familiares) | D12: Cant.
A13: C-03 | B13: Censo | C13: Promedio Ingresos Mensuales | D13: Cant.
B14: Perfil | C14: Valor Cuota de Sostenimiento mensual SIN IVA (cuota administración) | D14: $ Miles
B15: Perfil | C15: Valor Cuota de Sostenimiento mensual CON IVA (cuota administración) | D15: $ Miles
B16: Perfil | C16: Valor Consumo Mínimo mensual SIN IVA | D16: $ Miles
B17: Perfil | C17: Número de acciones para la venta que tiene su club a la fecha | D17: Cant.
B18: Perfil | C18: Valor aproximado de la acción | D18: $ Miles
B19: Perfil | C19: Valor Derecho | D19: $ Miles
B20: Perfil | C20: Valor Traspaso | D20: $ Miles
B21: Perfil | C21: Cantidad de derechos vendidos el año | D21: Cant.
B22: Perfil | C22: Tiene sindicato | D22: Si/No
A25: DEFINICIONES Y NOTAS
A26: D-01: 1=Club Ciudad, 2=Club Campestre, 3=Club Mixto
A27: D-02: Superficie total de la propiedad
A28: D-03: Suma de áreas techadas (Sedes, depósitos, etc)
A29: D-04: Sedes físicas independientes
A30: C-01: Acciones/Títulos con derecho a uso y pago
A31: C-02: Titulares + Cónyuges + Hijos + Beneficiarios
A32: C-03: Registros de portería/carnetización al mes

Sheet CAP1_Financiero_CAPEX
A1: CAPÍTULO 1: DESEMPEÑO FINANCIERO Y CAPEX
A2: (Variables del P&L para medir rentabilidad)
A4: Código | B4: Categoría | C4: Variable | D4: Unidad | E4: Valor a Capturar
A5: F-01 | B5: Ingresos | C5: Ingresos Totales Operativos | D5: $ Miles
A6: F-02 | B6: Ingresos | C6: Ingresos por Cuotas de Sostenimiento | D6: $ Miles
A7: F-03 | B7: Ingresos | C7: Ingresos por Alimentos y Bebidas | D7: $ Miles
B8: Ingresos | C8: Ingresos por Actividades Deportivas | D8: $ Miles
B9: Ingresos | C9: Ingresos por eventos | D9: $ Miles
B10: Ingresos | C10: Ingresos por torneos | D10: $ Miles
A11: F-04 | B11: Utilidad | C11: EBITDA | D11: $ Miles
A12: G-01 | B12: Gasto | C12: Gasto Total Servicios Públicos | D12: $ Miles
A13: G-02 | B13: Gasto | C13: Gasto en Mantenimiento | D13: $ Miles
A14: G-03 | B14: Gasto | C14: Gasto en Impuesto Predial | D14: $ Miles
C15: Valor de inventarios | D15: $ Miles
A16: I-01 | B16: Inversión | C16: Inversión en CapEx (Obras) | D16: $ Miles
A18: DEFINICIONES Y NOTAS METODOLÓGICAS
A19: F-01: Total facturado por todo concepto
A20: F-02: Excluir cuotas extraordinarias
A21: F-03: Restaurantes, bares y eventos
A22: F-04: Utilidad Operativa + Depreciación
A23: G-01: Agua + Luz + Gas + Residuos
A24: G-02: Insumos y contratos de reparaciones
A25: G-03: Valor pagado en el año
A26: I-01: Compras de maquinaria o construcción

Sheet CAP2_Nomina
A1: CAPÍTULO 2: ESTRUCTURA DE NÓMINA
A2: (Productividad - Sumar nómina de todos los cargos por bloque)
A4: Código | B4: Bloque | C4: Variable a Reportar | D4: Unidad | E4: Valor a Capturar
A5: N-01 | B5: Estratégica/Admin | C5: Nómina Estratégica/Admin | D5: $ Miles
A6: N-02 | B6: Operativa A&B | C6: Nómina Operativa A&B | D6: $ Miles
A7: N-03 | B7: Deportiva | C7: Nómina Deportiva | D7: $ Miles
A8: N-04 | B8: Soporte/Manto | C8: Nómina Soporte / Manto. | D8: $ Miles
A9: N-05 | B9: Estratégica/Admin | C9: Nómina Estratégica/Admin | D9: Cant.
A10: N-06 | B10: Operativa A&B | C10: Nómina Operativa A&B | D10: Cant.
A11: N-07 | B11: Deportiva | C11: Nómina Deportiva (otros) indefinidos | D11: Cant.
A12: N-08 | B12: Deportiva | C12: Nómina Deportiva (otros) otra modalidad | D12: Cant.
A13: N-09 | B13: Deportiva | C13: Nómina tenis y golf indefinidos | D13: Cant.
A14: N-10 | B14: Deportiva | C14: Nómina Deportiva otra modalidad | D14: Cant.
A15: N-11 | B15: Soporte/Manto | C15: Nómina Soporte / Manto. | D15: Cant.
A16: N-12 | B16: Todos | C16: Cantidad de empleados de cada club según rango salarial establecido dentro del rango : Hasta 1 SMLV | D16: Cant.
... A26: N-22 | B26: Todos | C26: Total empleados que tienen contrato a término indefinido y no trabajan tiempo completo | D26: Cant.
A30: QUÉ INCLUYE CADA BLOQUE
A31: N-01: Gerencia, Contabilidad, RRHH, Sistemas
A32: N-02: Cocina, Meseros, Stewards, Capitanes
A33: N-03: Profesores, Caddies, Directores Deportes
A34: N-04: Aseo, Vigilancia, Mantenimiento Campo
A36: INSTRUCCIONES
A37: Para cada bloque, sumar la nómina mensual promedio de todos los cargos correspondientes de su lista completa de personal (68 cargos tipo).

Sheet CAP3_Infraestructura_Uso
A1: CAPÍTULO 3: INFRAESTRUCTURA, DEPORTES Y USO
A2: (Variables para medir eficiencia por unidad de servicio)
A4: Código | B4: Deporte / Área | C4: Variable | D4: Unidad | E4: Valor a Capturar
A5: S-01 | B5: Golf | C5: Área de Mantenimiento Verde | D5: m²
A6: S-02 | B6: Golf | C6: Salidas (Rounds) al Mes | D6: Cant.
A7: S-03 | B7: Golf | C7: Cantidad de torneos realizados | D7: Cant.
A8: S-04 | B8: Tenis | C8: Número de Canchas Totales | D8: Cant.
A9: S-05 | B9: Tenis | C9: Ocupación canchas de tenis | D9: %
A10: S-06 | B10: Tenis | C10: Cantidad de torneos realizados | D10: Cant.
A11: S-07 | B11: Pádel | C11: Número de Canchas Totales | D11: Cant.
A12: S-08 | B12: Hípica | C12: Número de Pesebreras | D12: Cant.
A13: S-09 | B13: Fitness | C13: Número de Gimnasio | D13: Cant.
A14: S-10 | B14: A&B | C14: Capacidad de Sillas (Restaurantes) | D14: Cant.
A15: S-11 | B15: Natación | C15: Número de piscinas | D15: Cant.
A16: S-12 | B16: Natación | C16: Ocupación pisicina | D16: %
... A44: S-40 | B44: Ocio | C44: Km de ciclovia | D44: Km
A46: OBJETIVO DEL KPI
A47: S-01: Costo de mantenimiento por m² de césped
A48: S-02: Intensidad de uso del campo
A49: S-03: Densidad de socios por cancha
A50: S-04: Pesebreras
A51: S-05: Penetración del servicio en la comunidad
A52: S-06: Ventas por silla disponible

Sheet CAP4_Tarifas_Cartera
A1: CAPÍTULO 4: TARIFAS Y CARTERA
A2: (Comparativa de Mercado y Cobro)
A4: Código | B4: Descripción | C4: Unidad | D4: Cantidad | E4: Valor a Capturar
A5: T-01 | B5: Cuota Sostenimiento | C5: COP | D5: Mensual
A6: T-02 | B6: Tarifa invitado fin de semana | C6: COP | D6: Única
A7: T-03 | B7: Green Fee fin de semana | C7: COP | D7: Por uso
A8: T-04 | B8: Green Fee semana | C8: COP | D8: Por uso
A9: T-05 | B9: Clase Tenis privada | C9: COP | D9: Por hora
A10: T-06 | B10: Clase Tenis grupo | C10: COP | D10: Por uso
A11: T-07 | B11: Uso de gimnasio | C11: COP | D11: Por uso
A12: T-08 | B12: Pesebrera | C12: COP | D12: Por mes
A13: T-09 | B13: Corte caballero | C13: COP | D13: Por uso
A14: T-10 | B14: Corte dama | C14: COP | D14: Por uso
A15: T-11 | B15: Manicure | C15: COP | D15: Por uso
A16: T-12 | B16: Pedicura | C16: COP | D16: Por uso
A17: K-01 | B17: DSO | C17: Días | D17: Promedio
A19: DEFINICIONES
A20: T-01: Valor mensual base para socio titular
A21: T-02: Precio promedio de venta mercado actual
A22: T-03: Tarifa invitado fin de semana
A23: T-04: Tarifa promedio socio
A24: K-01: Promedio de días de cobro a socios

Sheet Información salarios
A1: CARGO | B1: CANTIDAD DE PERSONAS | C1: Directo | D1: Externo (prestación de servicios) | E1: SALARIO BÁSICO MENSUAL | F1: Valor Adicional Mensual Extralegal | G1: SALARIO TOTAL | H1: BENEFICIO MEDICINA PREPAGADA | I1: DEPORTES EN GENERAL | J1: GOLF | K1: TENIS | L1: RESTAURACION | M1: ATENCION FACILITIES | N1: ADMINISTRATIVO
A2: GERENTE GENERAL | B2: =+C2+D2 -> 6 | C2: =SUM(I2:N2) -> 1 | D2: 5 | G2: =SUM(E2:F2) -> 0 | N2: 1
A3: GERENTE FINANCIERO | B3: =+C3+D3 -> 0 | C3: =SUM(I3:N3) -> 0 | G3: =SUM(E3:F3) -> 0
A4: DIRECTOR FINANCIERO | B4: =+C4+D4 -> 0 | C4: =SUM(I4:N4) -> 0 | G4: =SUM(E4:F4) -> 0
A5: GERENTE OPERACIONES | B5: =+C5+D5 -> 0 | C5: =SUM(I5:N5) -> 0 | G5: =SUM(E5:F5) -> 0
A6: ASISTENTE DE GERENCIA | B6: =+C6+D6 -> 0 | C6: =SUM(I6:N6) -> 0 | G6: =SUM(E6:F6) -> 0
A7: SECRETARIA DE GERENCIA | B7: =+C7+D7 -> 0 | C7: =SUM(I7:N7) -> 0 | G7: =SUM(E7:F7) -> 0
A8: SECRETARIA DE JUNTA | B8: =+C8+D8 -> 0 | C8: =SUM(I8:N8) -> 0 | G8: =SUM(E8:F8) -> 0
A9: AUXILAR ADMINISTRATIVO | B9: =+C9+D9 -> 0 | C9: =SUM(I9:N9) -> 0 | G9: =SUM(E9:F9) -> 0
A10: RECEPCIONISTA | B10: =+C10+D10 -> 0 | C10: =SUM(I10:N10) -> 0 | G10: =SUM(E10:F10) -> 0
A11: JEFE DE COSTOS | B11: =+C11+D11 -> 0 | C11: =SUM(I11:N11) -> 0 | G11: =SUM(E11:F11) -> 0
A12: AUXILIAR DE COSTOS | B12: =+C12+D12 -> 0 | C12: =SUM(I12:N12) -> 0 | G12: =SUM(E12:F12) -> 0
A13: JEFE DE CARTERA | B13: =+C13+D13 -> 0 | C13: =SUM(I13:N13) -> 0 | G13: =SUM(E13:F13) -> 0
A14: ANALISTA DE CARTERA | B14: =+C14+D14 -> 0 | C14: =SUM(I14:N14) -> 0 | G14: =SUM(E14:F14) -> 0
... A34: VIGILANTE | B34: =+C34+D34 -> 0 | C34: =SUM(I34:N34) -> 0 | G34: =SUM(E34:F34) -> 0
A35: DIRECTOR DE DEPORTES | B35: =+C35+D35 -> 2 | C35: =SUM(I35:N35) -> 2 | G35: =SUM(E35:F35) -> 0 | J35: 1 | K35: 1
A36: DIRECTOR DE GOLF | B36: =+C36+D36 -> 0 | C36: =SUM(I36:N36) -> 0 | G36: =SUM(E36:F36) -> 0
A37: CAPATAZ DE GOLF | B37: =+C37+D37 -> 0 | C37: =SUM(I37:N37) -> 0 | G37: =SUM(E37:F37) -> 0
A38: DIRECTOR DE NATACIÓN | B38: =+C38+D38 -> 0 | C38: =SUM(I38:N38) -> 0 | G38: =SUM(E38:F38) -> 0
A39: DIRECTOR DE TENIS | B39: =+C39+D39 -> 0 | C39: =SUM(I39:N39) -> 0 | G39: =SUM(E39:F39) -> 0
A40: CADIE MASTER GOLF | B40: =+C40+D40 -> 10 | C40: =SUM(I40:N40) -> 10 | G40: =SUM(E40:F40) -> 0 | J40: 10
A41: CADIE MASTER TENIS | B41: =+C41+D41 -> 15 | C41: =SUM(I41:N41) -> 10 | D41: 5 | G41: =SUM(E41:F41) -> 0 | J41: 10
A42: PROFESOR DE GOLF | B42: =+C42+D42 -> 0 | C42: =SUM(I42:N42) -> 0 | G42: =SUM(E42:F42) -> 0
A43: PROFESOR DE NATACIÓN | B43: =+C43+D43 -> 0 | C43: =SUM(I43:N43) -> 0 | G43: =SUM(E43:F43) -> 0
A44: PROFESOR DE TENNIS | B44: =+C44+D44 -> 0 | C44: =SUM(I44:N44) -> 0 | G44: =SUM(E44:F44) -> 0
A45: GERENTE O ENCARGADO COMERCIAL | B45: =+C45+D45 -> 0 | C45: =SUM(I45:N45) -> 0 | G45: =SUM(E45:F45) -> 0
A46: JEFE DE RELACIONES PÚBLICAS | B46: =+C46+D46 -> 0 | C46: =SUM(I46:N46) -> 0 | G46: =SUM(E46:F46) -> 0
A47: JEFE DE ATENCIÓN AL SOCIO | B47: =+C47+D47 -> 0 | C47: =SUM(I47:N47) -> 0 | G47: =SUM(E47:F47) -> 0
A48: JEFE DE EVENTOS | B48: =+C48+D48 -> 0 | C48: =SUM(I48:N48) -> 0 | G48: =SUM(E48:F48) -> 0
A49: JEFE CASA CLUB | B49: =+C49+D49 -> 0 | C49: =SUM(I49:N49) -> 0 | G49: =SUM(E49:F49) -> 0
A50: JEFE DE ALIMENTOS Y BEBIDAS | B50: =+C50+D50 -> 0 | C50: =SUM(I50:N50) -> 0 | G50: =SUM(E50:F50) -> 0
A51: MAITRE | B51: =+C51+D51 -> 0 | C51: =SUM(I51:N51) -> 0 | G51: =SUM(E51:F51) -> 0
A52: CAPITÁN | B52: =+C52+D52 -> 0 | C52: =SUM(I52:N52) -> 0 | G52: =SUM(E52:F52) -> 0
A53: MESERO FIJO | B53: =+C53+D53 -> 0 | C53: =SUM(I53:N53) -> 0 | G53: =SUM(E53:F53) -> 0
... A69: OBRERO | B69: =+C69+D69 -> 0 | C69: =SUM(I69:N69) -> 0 | G69: =SUM(E69:F69) -> 0
